{
  "id": "pendulum-lab",
  "title": {
    "zh": "单摆实验室",
    "en": "Pendulum Lab"
  },
  "description": {
    "zh": "在 3D 摆架上抓起摆球放手，调摆长、质量、摆角、阻力与时间流速，去四个星球对比仿真周期与 T≈2π√(L/g)。",
    "en": "Grab the bob on a 3D rig, tune length, mass, angle, drag and time speed, and compare the simulated period with T≈2π√(L/g) on four planets."
  },
  "category": "physics",
  "levels": [
    "junior",
    "senior"
  ],
  "grades": [],
  "tags": [
    "单摆",
    "重力",
    "月球",
    "实验"
  ],
  "icon": "🪀",
  "order": 30
}
